LICENSE
README.md
setup.py
Lambda_REST_Client.egg-info/PKG-INFO
Lambda_REST_Client.egg-info/SOURCES.txt
Lambda_REST_Client.egg-info/dependency_links.txt
Lambda_REST_Client.egg-info/requires.txt
Lambda_REST_Client.egg-info/top_level.txt
lambda_rest/__init__.py
lambda_rest/_types.py
lambda_rest/base.py