Metadata-Version: 2.4
Name: Lambda-REST-Client
Version: 0.1.0.1
Summary: A simple client for calling Lambda REST endpoints
Home-page: https://github.com/a-jean-andreasian/Lambda-REST-Client
Author: Armen-Jean Andreasian
Author-email: armen.andreasian.dev@proton.me
Classifier: Programming Language :: Python :: 3
Classifier: License :: OSI Approved :: BSD License
Classifier: Operating System :: OS Independent
Requires-Python: >=3.8
License-File: LICENSE
Requires-Dist: aiohappyeyeballs==2.6.1
Requires-Dist: aiohttp==3.13.2
Requires-Dist: aiosignal==1.4.0
Requires-Dist: attrs==25.4.0
Requires-Dist: frozenlist==1.8.0
Requires-Dist: idna==3.11
Requires-Dist: multidict==6.7.0
Requires-Dist: propcache==0.4.1
Requires-Dist: yarl==1.22.0
Dynamic: author
Dynamic: author-email
Dynamic: classifier
Dynamic: description
Dynamic: description-content-type
Dynamic: home-page
Dynamic: license-file
Dynamic: requires-dist
Dynamic: requires-python
Dynamic: summary
